{
  "at": "2026-05-17T22:47:43.632Z",
  "passed": 11,
  "total": 11,
  "status": "OK 11/11",
  "results": [
    {
      "pass": true,
      "msg": "splash×9 + SW killer ok",
      "name": "Homepage 200 + splash + SW killer",
      "ms": 209
    },
    {
      "pass": true,
      "msg": "Hindi occurrences=0",
      "name": "JSON-LD has no Hindi",
      "ms": 29
    },
    {
      "pass": true,
      "msg": "HackedNewsPage-B3R9YFB1.js ok (3 proxies, sanitised)",
      "name": "Hacked News chunk has all 3 proxies + no javascript:",
      "ms": 128
    },
    {
      "pass": true,
      "msg": "12 releases",
      "name": "Backend /releases returns items",
      "ms": 4045
    },
    {
      "pass": true,
      "msg": "12 roadmaps",
      "name": "Backend /roadmaps returns ≥10",
      "ms": 1234
    },
    {
      "pass": true,
      "msg": "10 courses",
      "name": "Backend /courses returns items",
      "ms": 1128
    },
    {
      "pass": true,
      "msg": "status=200",
      "name": "Yahavi /chat/history reachable",
      "ms": 524
    },
    {
      "pass": true,
      "msg": "status=400",
      "name": "Sponsor order route alive (rejects bad payload)",
      "ms": 623
    },
    {
      "pass": true,
      "msg": "10/10 ok",
      "name": "Storefront 10 routes all 200",
      "ms": 113
    },
    {
      "pass": true,
      "msg": "6/6 sample feeds returned items",
      "name": "RSS proxy alive (≥3/6 sample feeds via codetabs)",
      "ms": 673
    },
    {
      "pass": true,
      "msg": "index-C7RWU5zY.js 200591B immutable",
      "name": "Main bundle present + ≥100KB + cache headers",
      "ms": 41
    }
  ]
}